{
	"configurations" : 
	[
		{
			"directories" : 
			[
				{
					"build" : ".",
					"minimumCMakeVersion" : 
					{
						"string" : "3.14"
					},
					"projectIndex" : 0,
					"source" : ".",
					"targetIndexes" : 
					[
						0
					]
				}
			],
			"name" : "Debug",
			"projects" : 
			[
				{
					"directoryIndexes" : 
					[
						0
					],
					"name" : "LinkedList",
					"targetIndexes" : 
					[
						0
					]
				}
			],
			"targets" : 
			[
				{
					"directoryIndex" : 0,
					"id" : "linked_list::@6890427a1f51a3e7e1df",
					"jsonFile" : "target-linked_list-Debug-746199e0a53b20aba3c6.json",
					"name" : "linked_list",
					"projectIndex" : 0
				}
			]
		}
	],
	"kind" : "codemodel",
	"paths" : 
	{
		"build" : "C:/Users/8337330/source/repos/01-exercicio-linked-list/out/build/x64-Debug",
		"source" : "C:/Users/8337330/source/repos/01-exercicio-linked-list"
	},
	"version" : 
	{
		"major" : 2,
		"minor" : 2
	}
}
